kerbrute/__init__.py
kerbrute/main.py
kerbrute-0.0.2.dist-info/LICENSE
kerbrute-0.0.2.dist-info/METADATA
kerbrute-0.0.2.dist-info/WHEEL
kerbrute-0.0.2.dist-info/entry_points.txt
kerbrute-0.0.2.dist-info/top_level.txt
kerbrute-0.0.2.dist-info/RECORD
