Metadata-Version: 2.1
Name: kerbrute
Version: 0.0.2
Summary: Kerberos bruteforce utility
Home-page: UNKNOWN
Author: Eloy Perez
Author-email: eloy.perez@tarlogic.com
License: UNKNOWN
Platform: UNKNOWN
Classifier: Programming Language :: Python :: 3
Classifier: License :: OSI Approved :: GNU General Public License v3 (GPLv3)
Classifier: Operating System :: OS Independent
Requires-Dist: impacket
